README.rst
setup.py
try_default.py
try_default.egg-info/PKG-INFO
try_default.egg-info/SOURCES.txt
try_default.egg-info/dependency_links.txt
try_default.egg-info/requires.txt
try_default.egg-info/top_level.txt