Metadata-Version: 1.1
Name: try-default
Version: 1.2
Summary: A microlibrary for handling exceptions
Home-page: https://github.com/jocke-l/try-default
Author: Joakim Saario
Author-email: joakim@5monkeys.se
License: 3-Clause BSD License
Keywords: util,functional,exceptions,microlibrary
Platform: UNKNOWN
Classifier: Programming Language :: Python :: 2.7
Classifier: Programming Language :: Python :: 3
Classifier: License :: OSI Approved :: BSD License
Classifier: Intended Audience :: Developers
